LICENSE.txt
README.txt
setup.py
SymQInfopy/__init__.py
SymQInfopy/density_matrix.py
SymQInfopy.egg-info/PKG-INFO
SymQInfopy.egg-info/SOURCES.txt
SymQInfopy.egg-info/dependency_links.txt
SymQInfopy.egg-info/requires.txt
SymQInfopy.egg-info/top_level.txt