Metadata-Version: 2.1
Name: SymQInfopy
Version: 0.0.2
Summary: Symbolic Quantum Information Calculations
Home-page: UNKNOWN
Author: jmstf94 (Dimitris Stefanopoulos)
Author-email: <jmstf94@gmail.com>
License: MIT
Keywords: python,quantum information,entropies,quantum,partial trace
Platform: UNKNOWN
Classifier: Development Status :: 1 - Planning
Classifier: Intended Audience :: Science/Research
Classifier: Programming Language :: Python :: 3
Classifier: Operating System :: Unix
Classifier: Operating System :: MacOS :: MacOS X
Classifier: Operating System :: Microsoft :: Windows
License-File: LICENSE.txt
